Metadata-Version: 1.1
Name: ignoregen
Version: 0.5
Summary: Generate Git ignore rules
Home-page: https://github.com/rcook/ignoregen
Author: Richard Cook
Author-email: rcook@rcook.org
License: MIT
Platform: UNKNOWN
Classifier: Development Status :: 3 - Alpha
Classifier: License :: OSI Approved :: MIT License
Classifier: Programming Language :: Python :: 2.7
